{"domain":"keplerwallpapers.online","url_count":1,"urls":[{"original_url":"https://keplerwallpapers.online","path":"/","query":"","snapshots":[{"timestamp":"20260430-092854","s3_prefix":"v2/keplerwallpapers.online/20260430-092854","files":["output.pdf","screenshot.png","warc.tgz"]},{"timestamp":"20260409-220026","s3_prefix":"v2/keplerwallpapers.online/20260409-220026","files":["output.pdf","screenshot.png","warc.tgz"]},{"timestamp":"20260402-111525","s3_prefix":"v2/keplerwallpapers.online/20260402-111525","files":["output.pdf","screenshot.png","warc.tgz"]},{"timestamp":"20260329-112716","s3_prefix":"v2/keplerwallpapers.online/20260329-112716","files":["output.pdf","screenshot.png","warc.tgz"]}]}]}