{"domain":"sourceware.org","url_count":7,"urls":[{"original_url":"https://sourceware.org/bugzilla/show_bug.cgi?id=33698","path":"/bugzilla/show_bug.cgi","query":"id=33698","snapshots":[{"timestamp":"20260425-205929","s3_prefix":"v2/sourceware.org/bugzilla/show_bug.cgi__q__id=33698/20260425-205929","files":["output.pdf","screenshot.png","warc.tgz"]},{"timestamp":"20260422-200729","s3_prefix":"v2/sourceware.org/bugzilla/show_bug.cgi__q__id=33698/20260422-200729","files":["output.pdf","screenshot.png","warc.tgz"]}]},{"original_url":"https://sourceware.org/bugzilla/show_bug.cgi?id=33700","path":"/bugzilla/show_bug.cgi","query":"id=33700","snapshots":[{"timestamp":"20260425-205925","s3_prefix":"v2/sourceware.org/bugzilla/show_bug.cgi__q__id=33700/20260425-205925","files":["output.pdf","screenshot.png","warc.tgz"]},{"timestamp":"20260422-200726","s3_prefix":"v2/sourceware.org/bugzilla/show_bug.cgi__q__id=33700/20260422-200726","files":["output.pdf","screenshot.png","warc.tgz"]}]},{"original_url":"https://sourceware.org/bugzilla/show_bug.cgi?id=33796","path":"/bugzilla/show_bug.cgi","query":"id=33796","snapshots":[{"timestamp":"20260429-150738","s3_prefix":"v2/sourceware.org/bugzilla/show_bug.cgi__q__id=33796/20260429-150738","files":["output.pdf","screenshot.png","warc.tgz"]},{"timestamp":"20260429-055049","s3_prefix":"v2/sourceware.org/bugzilla/show_bug.cgi__q__id=33796/20260429-055049","files":["output.pdf","screenshot.png","warc.tgz"]}]},{"original_url":"https://sourceware.org/git/gitweb.cgi?p=binutils-gdb.git%3Bh=ea4bc025abdba85a90e26e13f551c16a44bfa921","path":"/git/gitweb.cgi","query":"p=binutils-gdb.git%3Bh=ea4bc025abdba85a90e26e13f551c16a44bfa921","snapshots":[{"timestamp":"20260425-205931","s3_prefix":"v2/sourceware.org/git/gitweb.cgi__q__p=binutils-gdb.git%3Bh=ea4bc025abdba85a90e26e13f551c16a44bfa921/20260425-205931","files":["output.pdf","screenshot.png","warc.tgz"]},{"timestamp":"20260422-200725","s3_prefix":"v2/sourceware.org/git/gitweb.cgi__q__p=binutils-gdb.git%3Bh=ea4bc025abdba85a90e26e13f551c16a44bfa921/20260422-200725","files":["output.pdf","screenshot.png","warc.tgz"]}]},{"original_url":"https://sourceware.org/git?p=binutils-gdb.git%3Ba=commitdiff%3Bh=81e90cf63a10ad11772c2437c8f2a88f1a00c739","path":"/git","query":"p=binutils-gdb.git%3Ba=commitdiff%3Bh=81e90cf63a10ad11772c2437c8f2a88f1a00c739","snapshots":[{"timestamp":"20260425-205926","s3_prefix":"v2/sourceware.org/git__q__p=binutils-gdb.git%3Ba=commitdiff%3Bh=81e90cf63a10ad11772c2437c8f2a88f1a00c739/20260425-205926","files":["output.pdf","screenshot.png","warc.tgz"]},{"timestamp":"20260422-200729","s3_prefix":"v2/sourceware.org/git__q__p=binutils-gdb.git%3Ba=commitdiff%3Bh=81e90cf63a10ad11772c2437c8f2a88f1a00c739/20260422-200729","files":["output.pdf","screenshot.png","warc.tgz"]}]},{"original_url":"https://sourceware.org/git?p=binutils-gdb.git%3Ba=commitdiff%3Bh=ea4bc025abdba85a90e26e13f551c16a44bfa92","path":"/git","query":"p=binutils-gdb.git%3Ba=commitdiff%3Bh=ea4bc025abdba85a90e26e13f551c16a44bfa92","snapshots":[{"timestamp":"20260425-205931","s3_prefix":"v2/sourceware.org/git__q__p=binutils-gdb.git%3Ba=commitdiff%3Bh=ea4bc025abdba85a90e26e13f551c16a44bfa92/20260425-205931","files":["output.pdf","screenshot.png","warc.tgz"]},{"timestamp":"20260422-200733","s3_prefix":"v2/sourceware.org/git__q__p=binutils-gdb.git%3Ba=commitdiff%3Bh=ea4bc025abdba85a90e26e13f551c16a44bfa92/20260422-200733","files":["output.pdf","screenshot.png","warc.tgz"]}]},{"original_url":"https://sourceware.org/git?p=glibc.git%3Ba=blob_plain%3Bf=advisories%2FGLIBC-SA-2026-0001","path":"/git","query":"p=glibc.git%3Ba=blob_plain%3Bf=advisories%2FGLIBC-SA-2026-0001","snapshots":[{"timestamp":"20260429-150735","s3_prefix":"v2/sourceware.org/git__q__p=glibc.git%3Ba=blob_plain%3Bf=advisories%2FGLIBC-SA-2026-0001/20260429-150735","files":["output.pdf","screenshot.png","warc.tgz"]},{"timestamp":"20260429-055049","s3_prefix":"v2/sourceware.org/git__q__p=glibc.git%3Ba=blob_plain%3Bf=advisories%2FGLIBC-SA-2026-0001/20260429-055049","files":["output.pdf","screenshot.png","warc.tgz"]}]}]}