{"domain":"syst3mfailure.io","url_count":1,"urls":[{"original_url":"https://syst3mfailure.io/rbtree-family-drama","path":"/rbtree-family-drama","query":"","snapshots":[{"timestamp":"20260410-195908","s3_prefix":"v2/syst3mfailure.io/rbtree-family-drama/20260410-195908","files":["output.pdf","screenshot.png","warc.tgz"]},{"timestamp":"20260402-235219","s3_prefix":"v2/syst3mfailure.io/rbtree-family-drama/20260402-235219","files":["output.pdf","screenshot.png","warc.tgz"]},{"timestamp":"20260329-031717","s3_prefix":"v2/syst3mfailure.io/rbtree-family-drama/20260329-031717","files":["output.pdf","screenshot.png","warc.tgz"]}]}]}