{"domain":"www.kb.cert.org","url_count":2,"urls":[{"original_url":"https://www.kb.cert.org/vuls/id/221883","path":"/vuls/id/221883","query":"","snapshots":[{"timestamp":"20260403-191001","s3_prefix":"v2/www.kb.cert.org/vuls/id/221883/20260403-191001","files":["output.pdf","screenshot.png","warc.tgz"]},{"timestamp":"20260331-185432","s3_prefix":"v2/www.kb.cert.org/vuls/id/221883/20260331-185432","files":["output.pdf","screenshot.png","warc.tgz"]}]},{"original_url":"https://www.kb.cert.org/vuls/id/507216","path":"/vuls/id/507216","query":"","snapshots":[{"timestamp":"20260403-222414","s3_prefix":"v2/www.kb.cert.org/vuls/id/507216/20260403-222414","files":["output.pdf","screenshot.png","warc.tgz"]}]}]}