{"domain":"yasr.sourceforge.net","url_count":1,"urls":[{"original_url":"https://yasr.sourceforge.net","path":"/","query":"","snapshots":[{"timestamp":"20260401-140927","s3_prefix":"v2/yasr.sourceforge.net/20260401-140927","files":["output.pdf","screenshot.png","warc.tgz"]},{"timestamp":"20260330-174523","s3_prefix":"v2/yasr.sourceforge.net/20260330-174523","files":["output.pdf","screenshot.png","warc.tgz"]},{"timestamp":"20260329-134649","s3_prefix":"v2/yasr.sourceforge.net/20260329-134649","files":["output.pdf","screenshot.png","warc.tgz"]}]}]}